{
  "defaultSeverity": "warning",
  "extends": [
    "tslint:recommended",
    "tslint-no-unused-expression-chai"
  ],
  "linterOptions": {
    "exclude": [
      "node_modules/**"
    ]
  },
  "rules": {
    "indent": [true, "spaces", 2],
    "interface-name": false,
    "no-consecutive-blank-lines": false,
    "object-literal-sort-keys": false,
    "only-arrow-functions": false,
    "ordered-imports": false,
    "quotemark": [true, "single"],
    "semicolon": true,
    "trailing-comma": [
      true,
      {
        "multiline": {
          "arrays": "always"
        }
      }
    ],
    "variable-name": [
      true,
      "ban-keywords",
      "check-format",
      "allow-leading-underscore"
    ],
    "quotemark": [
      true,
      "single",
      "jsx-double",
      "avoid-template",
      "avoid-escape"
    ]
  }
}
